[
    {
        "id": 1,
        "name": "Instituto Federal do Espirito Santo",
        "description": null,
        "short_name": "IFES",
        "campus": null
    },
    {
        "id": 2,
        "name": "Voluntário",
        "description": null,
        "short_name": null,
        "campus": null
    },
    {
        "id": 3,
        "name": "CNPq",
        "description": null,
        "short_name": null,
        "campus": null
    },
    {
        "id": 4,
        "name": "Fapes",
        "description": null,
        "short_name": null,
        "campus": null
    },
    {
        "id": 5,
        "name": "Ifes",
        "description": null,
        "short_name": null,
        "campus": null
    },
    {
        "id": 6,
        "name": "Universidade Federal do Espírito Santo, UFES, Brasil",
        "description": null,
        "short_name": null,
        "campus": null
    },
    {
        "id": 7,
        "name": "(Carga Horária: 480h)",
        "description": null,
        "short_name": null,
        "campus": null
    },
    {
        "id": 8,
        "name": "Universidade Federal da Bahia, UFBA, Brasil",
        "description": null,
        "short_name": null,
        "campus": null
    },
    {
        "id": 9,
        "name": "(Carga Horária: 360h)",
        "description": null,
        "short_name": null,
        "campus": null
    },
    {
        "id": 10,
        "name": "Instituto Federal de Educação, Ciência e Tecnologia do Espírito Santo, IFES, Brasil",
        "description": null,
        "short_name": null,
        "campus": null
    },
    {
        "id": 11,
        "name": "Escola Tecnica Federal do Espirito Santo, ETFES, Brasil",
        "description": null,
        "short_name": null,
        "campus": null
    },
    {
        "id": 12,
        "name": "(Carga Horária: 465h)",
        "description": null,
        "short_name": null,
        "campus": null
    },
    {
        "id": 13,
        "name": "Centro Federal de Educação Tecnológica do Espírito Santo, CEFETES, Brasil",
        "description": null,
        "short_name": null,
        "campus": null
    },
    {
        "id": 14,
        "name": "Escola Politécnica da Universidade de São Paulo, EPUSP, Brasil",
        "description": null,
        "short_name": null,
        "campus": null
    },
    {
        "id": 15,
        "name": "Departamento de Engenharia Elétrica, UFES, Brasil",
        "description": null,
        "short_name": null,
        "campus": null
    },
    {
        "id": 16,
        "name": "Instituto Tecnológico de Aeronáutica, ITA, Brasil",
        "description": null,
        "short_name": null,
        "campus": null
    },
    {
        "id": 17,
        "name": "(Carga Horária: 632h)",
        "description": null,
        "short_name": null,
        "campus": null
    },
    {
        "id": 18,
        "name": "Escola Técnica Federal do Espírito Santo, ETF-ES, Brasil",
        "description": null,
        "short_name": null,
        "campus": null
    },
    {
        "id": 19,
        "name": "Universidade Federal de São João Del Rei, UFSJ, Brasil",
        "description": null,
        "short_name": null,
        "campus": null
    },
    {
        "id": 20,
        "name": "(Carga Horária: 448h)",
        "description": null,
        "short_name": null,
        "campus": null
    },
    {
        "id": 21,
        "name": "Universidade Federal de Viçosa, UFV, Brasil",
        "description": null,
        "short_name": null,
        "campus": null
    },
    {
        "id": 22,
        "name": "Escola de Aplicação, FAFIU, Brasil",
        "description": null,
        "short_name": null,
        "campus": null
    },
    {
        "id": 23,
        "name": "Universidad Nacional del Centro del Perú, UNCP, Peru",
        "description": null,
        "short_name": null,
        "campus": null
    },
    {
        "id": 24,
        "name": "Claretiano, CLARETIANO, Peru",
        "description": null,
        "short_name": null,
        "campus": null
    },
    {
        "id": 25,
        "name": "Universidade Federal de Pernambuco, UFPE, Brasil",
        "description": null,
        "short_name": null,
        "campus": null
    },
    {
        "id": 26,
        "name": "Universidade de Pernambuco, UPE, Brasil",
        "description": null,
        "short_name": null,
        "campus": null
    },
    {
        "id": 27,
        "name": "Instituto Federal de Pernambuco, IFPE, Brasil",
        "description": null,
        "short_name": null,
        "campus": null
    }
]