{
    "metadata": {
        "generated_at": "2026-04-04T20:12:19.334547+00:00",
        "sources": {
            "researchers": "data/exports/researchers_canonical.json",
            "initiatives": "data/exports/initiatives_canonical.json",
            "research_groups": "data/exports/research_groups_canonical.json",
            "advisorships": "data/exports/advisorships_canonical.json"
        },
        "scope": {
            "type": "research_group",
            "graph_type": "collaboration",
            "research_group": {
                "id": 10,
                "name": "Aracê - Grupo de Pesquisa em Educação, Sociedade e História Ambiental",
                "short_name": "Aracê ",
                "campus_name": "Vitória",
                "member_count": 17
            }
        },
        "weight_definition": "Each edge weight equals the total number of collaboration evidences between two people inside the research group. Every shared research project, shared article, and orientation adds 1 to the edge weight.",
        "relation_types": {
            "orientation": "Supervisor and student connected by an advisorship/orientation.",
            "project": "People who appear together in the same research project team.",
            "article": "People who are linked to the same article record."
        }
    },
    "graph_stats": {
        "nodes": 17,
        "edges": 0,
        "isolated_nodes": 17,
        "connected_components": 17,
        "largest_component_size": 1,
        "relation_event_totals": {
            "orientation": 0,
            "project": 0,
            "article": 0
        },
        "edge_relation_presence": {
            "orientation": 0,
            "project": 0,
            "article": 0
        },
        "classification_distribution": {
            "researcher": 9,
            "student": 8
        },
        "campus_distribution": {
            "Vitória": 12,
            "Vila Velha": 2,
            "Alegre": 2,
            "Cefor": 1
        },
        "top_people_by_weighted_degree": [
            {
                "id": 152,
                "name": "Aramis Cortes De Araujo Junior",
                "classification": "researcher",
                "campus_name": "Alegre",
                "weighted_degree": 0,
                "degree": 0
            },
            {
                "id": 1689,
                "name": "Levanildo Silva de Oliveira",
                "classification": "student",
                "campus_name": "Cefor",
                "weighted_degree": 0,
                "degree": 0
            },
            {
                "id": 18,
                "name": "Eduardo Fausto Kuster Cid",
                "classification": "researcher",
                "campus_name": "Vitória",
                "weighted_degree": 0,
                "degree": 0
            },
            {
                "id": 19,
                "name": "Sabrine Lino Pinto",
                "classification": "researcher",
                "campus_name": "Vila Velha",
                "weighted_degree": 0,
                "degree": 0
            },
            {
                "id": 1909,
                "name": "Adriana Luisa Lourenço Falcão",
                "classification": "researcher",
                "campus_name": "Vitória",
                "weighted_degree": 0,
                "degree": 0
            },
            {
                "id": 1910,
                "name": "Camille Altoé Calatrone",
                "classification": "researcher",
                "campus_name": "Vila Velha",
                "weighted_degree": 0,
                "degree": 0
            },
            {
                "id": 1911,
                "name": "Izabella Capucho Céllia Guimarães",
                "classification": "student",
                "campus_name": "Vitória",
                "weighted_degree": 0,
                "degree": 0
            },
            {
                "id": 1912,
                "name": "Lucas Rodrigues Barreto",
                "classification": "researcher",
                "campus_name": "Vitória",
                "weighted_degree": 0,
                "degree": 0
            },
            {
                "id": 1913,
                "name": "Andressa Lemos Fernandes",
                "classification": "researcher",
                "campus_name": "Vitória",
                "weighted_degree": 0,
                "degree": 0
            },
            {
                "id": 1914,
                "name": "Geisa Correa Louback",
                "classification": "researcher",
                "campus_name": "Alegre",
                "weighted_degree": 0,
                "degree": 0
            },
            {
                "id": 1915,
                "name": "Roberto Márcio da Silveira",
                "classification": "researcher",
                "campus_name": "Vitória",
                "weighted_degree": 0,
                "degree": 0
            },
            {
                "id": 1916,
                "name": "Ana Carolina dos Reis Santos",
                "classification": "student",
                "campus_name": "Vitória",
                "weighted_degree": 0,
                "degree": 0
            },
            {
                "id": 1917,
                "name": "Jéssica Benedita Entrin Câmara",
                "classification": "student",
                "campus_name": "Vitória",
                "weighted_degree": 0,
                "degree": 0
            },
            {
                "id": 1918,
                "name": "Layane de Oliveira Ferreira",
                "classification": "student",
                "campus_name": "Vitória",
                "weighted_degree": 0,
                "degree": 0
            },
            {
                "id": 1919,
                "name": "Letícia Ferreira Dias",
                "classification": "student",
                "campus_name": "Vitória",
                "weighted_degree": 0,
                "degree": 0
            },
            {
                "id": 1920,
                "name": "Maria Aparecida Beltrame Milanesi",
                "classification": "student",
                "campus_name": "Vitória",
                "weighted_degree": 0,
                "degree": 0
            },
            {
                "id": 1921,
                "name": "Yasmin dos Santos Dias",
                "classification": "student",
                "campus_name": "Vitória",
                "weighted_degree": 0,
                "degree": 0
            }
        ],
        "complex_network_metrics": {
            "density": 0,
            "average_clustering": 0.0,
            "transitivity": 0,
            "assortativity_by_classification": null,
            "community_count": 17,
            "largest_community_size": 1,
            "community_detection_mode": "isolated_nodes",
            "modularity": null,
            "hub_count": 0,
            "articulation_point_count": 0,
            "bridge_edge_count": 0,
            "betweenness_mode": "not_applicable"
        },
        "top_hubs_by_degree_centrality": [
            {
                "id": 152,
                "name": "Aramis Cortes De Araujo Junior",
                "classification": "researcher",
                "campus_name": "Alegre",
                "degree_centrality": 0.0,
                "weighted_degree": 0,
                "degree": 0
            },
            {
                "id": 1689,
                "name": "Levanildo Silva de Oliveira",
                "classification": "student",
                "campus_name": "Cefor",
                "degree_centrality": 0.0,
                "weighted_degree": 0,
                "degree": 0
            },
            {
                "id": 18,
                "name": "Eduardo Fausto Kuster Cid",
                "classification": "researcher",
                "campus_name": "Vitória",
                "degree_centrality": 0.0,
                "weighted_degree": 0,
                "degree": 0
            },
            {
                "id": 19,
                "name": "Sabrine Lino Pinto",
                "classification": "researcher",
                "campus_name": "Vila Velha",
                "degree_centrality": 0.0,
                "weighted_degree": 0,
                "degree": 0
            },
            {
                "id": 1909,
                "name": "Adriana Luisa Lourenço Falcão",
                "classification": "researcher",
                "campus_name": "Vitória",
                "degree_centrality": 0.0,
                "weighted_degree": 0,
                "degree": 0
            },
            {
                "id": 1910,
                "name": "Camille Altoé Calatrone",
                "classification": "researcher",
                "campus_name": "Vila Velha",
                "degree_centrality": 0.0,
                "weighted_degree": 0,
                "degree": 0
            },
            {
                "id": 1911,
                "name": "Izabella Capucho Céllia Guimarães",
                "classification": "student",
                "campus_name": "Vitória",
                "degree_centrality": 0.0,
                "weighted_degree": 0,
                "degree": 0
            },
            {
                "id": 1912,
                "name": "Lucas Rodrigues Barreto",
                "classification": "researcher",
                "campus_name": "Vitória",
                "degree_centrality": 0.0,
                "weighted_degree": 0,
                "degree": 0
            },
            {
                "id": 1913,
                "name": "Andressa Lemos Fernandes",
                "classification": "researcher",
                "campus_name": "Vitória",
                "degree_centrality": 0.0,
                "weighted_degree": 0,
                "degree": 0
            },
            {
                "id": 1914,
                "name": "Geisa Correa Louback",
                "classification": "researcher",
                "campus_name": "Alegre",
                "degree_centrality": 0.0,
                "weighted_degree": 0,
                "degree": 0
            },
            {
                "id": 1915,
                "name": "Roberto Márcio da Silveira",
                "classification": "researcher",
                "campus_name": "Vitória",
                "degree_centrality": 0.0,
                "weighted_degree": 0,
                "degree": 0
            },
            {
                "id": 1916,
                "name": "Ana Carolina dos Reis Santos",
                "classification": "student",
                "campus_name": "Vitória",
                "degree_centrality": 0.0,
                "weighted_degree": 0,
                "degree": 0
            },
            {
                "id": 1917,
                "name": "Jéssica Benedita Entrin Câmara",
                "classification": "student",
                "campus_name": "Vitória",
                "degree_centrality": 0.0,
                "weighted_degree": 0,
                "degree": 0
            },
            {
                "id": 1918,
                "name": "Layane de Oliveira Ferreira",
                "classification": "student",
                "campus_name": "Vitória",
                "degree_centrality": 0.0,
                "weighted_degree": 0,
                "degree": 0
            },
            {
                "id": 1919,
                "name": "Letícia Ferreira Dias",
                "classification": "student",
                "campus_name": "Vitória",
                "degree_centrality": 0.0,
                "weighted_degree": 0,
                "degree": 0
            },
            {
                "id": 1920,
                "name": "Maria Aparecida Beltrame Milanesi",
                "classification": "student",
                "campus_name": "Vitória",
                "degree_centrality": 0.0,
                "weighted_degree": 0,
                "degree": 0
            },
            {
                "id": 1921,
                "name": "Yasmin dos Santos Dias",
                "classification": "student",
                "campus_name": "Vitória",
                "degree_centrality": 0.0,
                "weighted_degree": 0,
                "degree": 0
            }
        ],
        "top_brokers_by_betweenness": [
            {
                "id": 152,
                "name": "Aramis Cortes De Araujo Junior",
                "classification": "researcher",
                "campus_name": "Alegre",
                "betweenness_centrality": 0.0,
                "weighted_degree": 0,
                "degree": 0
            },
            {
                "id": 1689,
                "name": "Levanildo Silva de Oliveira",
                "classification": "student",
                "campus_name": "Cefor",
                "betweenness_centrality": 0.0,
                "weighted_degree": 0,
                "degree": 0
            },
            {
                "id": 18,
                "name": "Eduardo Fausto Kuster Cid",
                "classification": "researcher",
                "campus_name": "Vitória",
                "betweenness_centrality": 0.0,
                "weighted_degree": 0,
                "degree": 0
            },
            {
                "id": 19,
                "name": "Sabrine Lino Pinto",
                "classification": "researcher",
                "campus_name": "Vila Velha",
                "betweenness_centrality": 0.0,
                "weighted_degree": 0,
                "degree": 0
            },
            {
                "id": 1909,
                "name": "Adriana Luisa Lourenço Falcão",
                "classification": "researcher",
                "campus_name": "Vitória",
                "betweenness_centrality": 0.0,
                "weighted_degree": 0,
                "degree": 0
            },
            {
                "id": 1910,
                "name": "Camille Altoé Calatrone",
                "classification": "researcher",
                "campus_name": "Vila Velha",
                "betweenness_centrality": 0.0,
                "weighted_degree": 0,
                "degree": 0
            },
            {
                "id": 1911,
                "name": "Izabella Capucho Céllia Guimarães",
                "classification": "student",
                "campus_name": "Vitória",
                "betweenness_centrality": 0.0,
                "weighted_degree": 0,
                "degree": 0
            },
            {
                "id": 1912,
                "name": "Lucas Rodrigues Barreto",
                "classification": "researcher",
                "campus_name": "Vitória",
                "betweenness_centrality": 0.0,
                "weighted_degree": 0,
                "degree": 0
            },
            {
                "id": 1913,
                "name": "Andressa Lemos Fernandes",
                "classification": "researcher",
                "campus_name": "Vitória",
                "betweenness_centrality": 0.0,
                "weighted_degree": 0,
                "degree": 0
            },
            {
                "id": 1914,
                "name": "Geisa Correa Louback",
                "classification": "researcher",
                "campus_name": "Alegre",
                "betweenness_centrality": 0.0,
                "weighted_degree": 0,
                "degree": 0
            },
            {
                "id": 1915,
                "name": "Roberto Márcio da Silveira",
                "classification": "researcher",
                "campus_name": "Vitória",
                "betweenness_centrality": 0.0,
                "weighted_degree": 0,
                "degree": 0
            },
            {
                "id": 1916,
                "name": "Ana Carolina dos Reis Santos",
                "classification": "student",
                "campus_name": "Vitória",
                "betweenness_centrality": 0.0,
                "weighted_degree": 0,
                "degree": 0
            },
            {
                "id": 1917,
                "name": "Jéssica Benedita Entrin Câmara",
                "classification": "student",
                "campus_name": "Vitória",
                "betweenness_centrality": 0.0,
                "weighted_degree": 0,
                "degree": 0
            },
            {
                "id": 1918,
                "name": "Layane de Oliveira Ferreira",
                "classification": "student",
                "campus_name": "Vitória",
                "betweenness_centrality": 0.0,
                "weighted_degree": 0,
                "degree": 0
            },
            {
                "id": 1919,
                "name": "Letícia Ferreira Dias",
                "classification": "student",
                "campus_name": "Vitória",
                "betweenness_centrality": 0.0,
                "weighted_degree": 0,
                "degree": 0
            },
            {
                "id": 1920,
                "name": "Maria Aparecida Beltrame Milanesi",
                "classification": "student",
                "campus_name": "Vitória",
                "betweenness_centrality": 0.0,
                "weighted_degree": 0,
                "degree": 0
            },
            {
                "id": 1921,
                "name": "Yasmin dos Santos Dias",
                "classification": "student",
                "campus_name": "Vitória",
                "betweenness_centrality": 0.0,
                "weighted_degree": 0,
                "degree": 0
            }
        ],
        "communities": [
            {
                "community_id": 0,
                "size": 1
            },
            {
                "community_id": 1,
                "size": 1
            },
            {
                "community_id": 2,
                "size": 1
            },
            {
                "community_id": 3,
                "size": 1
            },
            {
                "community_id": 4,
                "size": 1
            },
            {
                "community_id": 5,
                "size": 1
            },
            {
                "community_id": 6,
                "size": 1
            },
            {
                "community_id": 7,
                "size": 1
            },
            {
                "community_id": 8,
                "size": 1
            },
            {
                "community_id": 9,
                "size": 1
            },
            {
                "community_id": 10,
                "size": 1
            },
            {
                "community_id": 11,
                "size": 1
            },
            {
                "community_id": 12,
                "size": 1
            },
            {
                "community_id": 13,
                "size": 1
            },
            {
                "community_id": 14,
                "size": 1
            },
            {
                "community_id": 15,
                "size": 1
            },
            {
                "community_id": 16,
                "size": 1
            }
        ]
    },
    "graph": {
        "directed": false,
        "multigraph": false,
        "graph": {
            "_complex_network_summary": {
                "metrics": {
                    "density": 0,
                    "average_clustering": 0.0,
                    "transitivity": 0,
                    "assortativity_by_classification": null,
                    "community_count": 17,
                    "largest_community_size": 1,
                    "community_detection_mode": "isolated_nodes",
                    "modularity": null,
                    "hub_count": 0,
                    "articulation_point_count": 0,
                    "bridge_edge_count": 0,
                    "betweenness_mode": "not_applicable"
                },
                "top_hubs": [
                    {
                        "id": 152,
                        "name": "Aramis Cortes De Araujo Junior",
                        "classification": "researcher",
                        "campus_name": "Alegre",
                        "degree_centrality": 0.0,
                        "weighted_degree": 0,
                        "degree": 0
                    },
                    {
                        "id": 1689,
                        "name": "Levanildo Silva de Oliveira",
                        "classification": "student",
                        "campus_name": "Cefor",
                        "degree_centrality": 0.0,
                        "weighted_degree": 0,
                        "degree": 0
                    },
                    {
                        "id": 18,
                        "name": "Eduardo Fausto Kuster Cid",
                        "classification": "researcher",
                        "campus_name": "Vitória",
                        "degree_centrality": 0.0,
                        "weighted_degree": 0,
                        "degree": 0
                    },
                    {
                        "id": 19,
                        "name": "Sabrine Lino Pinto",
                        "classification": "researcher",
                        "campus_name": "Vila Velha",
                        "degree_centrality": 0.0,
                        "weighted_degree": 0,
                        "degree": 0
                    },
                    {
                        "id": 1909,
                        "name": "Adriana Luisa Lourenço Falcão",
                        "classification": "researcher",
                        "campus_name": "Vitória",
                        "degree_centrality": 0.0,
                        "weighted_degree": 0,
                        "degree": 0
                    },
                    {
                        "id": 1910,
                        "name": "Camille Altoé Calatrone",
                        "classification": "researcher",
                        "campus_name": "Vila Velha",
                        "degree_centrality": 0.0,
                        "weighted_degree": 0,
                        "degree": 0
                    },
                    {
                        "id": 1911,
                        "name": "Izabella Capucho Céllia Guimarães",
                        "classification": "student",
                        "campus_name": "Vitória",
                        "degree_centrality": 0.0,
                        "weighted_degree": 0,
                        "degree": 0
                    },
                    {
                        "id": 1912,
                        "name": "Lucas Rodrigues Barreto",
                        "classification": "researcher",
                        "campus_name": "Vitória",
                        "degree_centrality": 0.0,
                        "weighted_degree": 0,
                        "degree": 0
                    },
                    {
                        "id": 1913,
                        "name": "Andressa Lemos Fernandes",
                        "classification": "researcher",
                        "campus_name": "Vitória",
                        "degree_centrality": 0.0,
                        "weighted_degree": 0,
                        "degree": 0
                    },
                    {
                        "id": 1914,
                        "name": "Geisa Correa Louback",
                        "classification": "researcher",
                        "campus_name": "Alegre",
                        "degree_centrality": 0.0,
                        "weighted_degree": 0,
                        "degree": 0
                    },
                    {
                        "id": 1915,
                        "name": "Roberto Márcio da Silveira",
                        "classification": "researcher",
                        "campus_name": "Vitória",
                        "degree_centrality": 0.0,
                        "weighted_degree": 0,
                        "degree": 0
                    },
                    {
                        "id": 1916,
                        "name": "Ana Carolina dos Reis Santos",
                        "classification": "student",
                        "campus_name": "Vitória",
                        "degree_centrality": 0.0,
                        "weighted_degree": 0,
                        "degree": 0
                    },
                    {
                        "id": 1917,
                        "name": "Jéssica Benedita Entrin Câmara",
                        "classification": "student",
                        "campus_name": "Vitória",
                        "degree_centrality": 0.0,
                        "weighted_degree": 0,
                        "degree": 0
                    },
                    {
                        "id": 1918,
                        "name": "Layane de Oliveira Ferreira",
                        "classification": "student",
                        "campus_name": "Vitória",
                        "degree_centrality": 0.0,
                        "weighted_degree": 0,
                        "degree": 0
                    },
                    {
                        "id": 1919,
                        "name": "Letícia Ferreira Dias",
                        "classification": "student",
                        "campus_name": "Vitória",
                        "degree_centrality": 0.0,
                        "weighted_degree": 0,
                        "degree": 0
                    },
                    {
                        "id": 1920,
                        "name": "Maria Aparecida Beltrame Milanesi",
                        "classification": "student",
                        "campus_name": "Vitória",
                        "degree_centrality": 0.0,
                        "weighted_degree": 0,
                        "degree": 0
                    },
                    {
                        "id": 1921,
                        "name": "Yasmin dos Santos Dias",
                        "classification": "student",
                        "campus_name": "Vitória",
                        "degree_centrality": 0.0,
                        "weighted_degree": 0,
                        "degree": 0
                    }
                ],
                "top_brokers": [
                    {
                        "id": 152,
                        "name": "Aramis Cortes De Araujo Junior",
                        "classification": "researcher",
                        "campus_name": "Alegre",
                        "betweenness_centrality": 0.0,
                        "weighted_degree": 0,
                        "degree": 0
                    },
                    {
                        "id": 1689,
                        "name": "Levanildo Silva de Oliveira",
                        "classification": "student",
                        "campus_name": "Cefor",
                        "betweenness_centrality": 0.0,
                        "weighted_degree": 0,
                        "degree": 0
                    },
                    {
                        "id": 18,
                        "name": "Eduardo Fausto Kuster Cid",
                        "classification": "researcher",
                        "campus_name": "Vitória",
                        "betweenness_centrality": 0.0,
                        "weighted_degree": 0,
                        "degree": 0
                    },
                    {
                        "id": 19,
                        "name": "Sabrine Lino Pinto",
                        "classification": "researcher",
                        "campus_name": "Vila Velha",
                        "betweenness_centrality": 0.0,
                        "weighted_degree": 0,
                        "degree": 0
                    },
                    {
                        "id": 1909,
                        "name": "Adriana Luisa Lourenço Falcão",
                        "classification": "researcher",
                        "campus_name": "Vitória",
                        "betweenness_centrality": 0.0,
                        "weighted_degree": 0,
                        "degree": 0
                    },
                    {
                        "id": 1910,
                        "name": "Camille Altoé Calatrone",
                        "classification": "researcher",
                        "campus_name": "Vila Velha",
                        "betweenness_centrality": 0.0,
                        "weighted_degree": 0,
                        "degree": 0
                    },
                    {
                        "id": 1911,
                        "name": "Izabella Capucho Céllia Guimarães",
                        "classification": "student",
                        "campus_name": "Vitória",
                        "betweenness_centrality": 0.0,
                        "weighted_degree": 0,
                        "degree": 0
                    },
                    {
                        "id": 1912,
                        "name": "Lucas Rodrigues Barreto",
                        "classification": "researcher",
                        "campus_name": "Vitória",
                        "betweenness_centrality": 0.0,
                        "weighted_degree": 0,
                        "degree": 0
                    },
                    {
                        "id": 1913,
                        "name": "Andressa Lemos Fernandes",
                        "classification": "researcher",
                        "campus_name": "Vitória",
                        "betweenness_centrality": 0.0,
                        "weighted_degree": 0,
                        "degree": 0
                    },
                    {
                        "id": 1914,
                        "name": "Geisa Correa Louback",
                        "classification": "researcher",
                        "campus_name": "Alegre",
                        "betweenness_centrality": 0.0,
                        "weighted_degree": 0,
                        "degree": 0
                    },
                    {
                        "id": 1915,
                        "name": "Roberto Márcio da Silveira",
                        "classification": "researcher",
                        "campus_name": "Vitória",
                        "betweenness_centrality": 0.0,
                        "weighted_degree": 0,
                        "degree": 0
                    },
                    {
                        "id": 1916,
                        "name": "Ana Carolina dos Reis Santos",
                        "classification": "student",
                        "campus_name": "Vitória",
                        "betweenness_centrality": 0.0,
                        "weighted_degree": 0,
                        "degree": 0
                    },
                    {
                        "id": 1917,
                        "name": "Jéssica Benedita Entrin Câmara",
                        "classification": "student",
                        "campus_name": "Vitória",
                        "betweenness_centrality": 0.0,
                        "weighted_degree": 0,
                        "degree": 0
                    },
                    {
                        "id": 1918,
                        "name": "Layane de Oliveira Ferreira",
                        "classification": "student",
                        "campus_name": "Vitória",
                        "betweenness_centrality": 0.0,
                        "weighted_degree": 0,
                        "degree": 0
                    },
                    {
                        "id": 1919,
                        "name": "Letícia Ferreira Dias",
                        "classification": "student",
                        "campus_name": "Vitória",
                        "betweenness_centrality": 0.0,
                        "weighted_degree": 0,
                        "degree": 0
                    },
                    {
                        "id": 1920,
                        "name": "Maria Aparecida Beltrame Milanesi",
                        "classification": "student",
                        "campus_name": "Vitória",
                        "betweenness_centrality": 0.0,
                        "weighted_degree": 0,
                        "degree": 0
                    },
                    {
                        "id": 1921,
                        "name": "Yasmin dos Santos Dias",
                        "classification": "student",
                        "campus_name": "Vitória",
                        "betweenness_centrality": 0.0,
                        "weighted_degree": 0,
                        "degree": 0
                    }
                ],
                "communities": [
                    {
                        "community_id": 0,
                        "size": 1
                    },
                    {
                        "community_id": 1,
                        "size": 1
                    },
                    {
                        "community_id": 2,
                        "size": 1
                    },
                    {
                        "community_id": 3,
                        "size": 1
                    },
                    {
                        "community_id": 4,
                        "size": 1
                    },
                    {
                        "community_id": 5,
                        "size": 1
                    },
                    {
                        "community_id": 6,
                        "size": 1
                    },
                    {
                        "community_id": 7,
                        "size": 1
                    },
                    {
                        "community_id": 8,
                        "size": 1
                    },
                    {
                        "community_id": 9,
                        "size": 1
                    },
                    {
                        "community_id": 10,
                        "size": 1
                    },
                    {
                        "community_id": 11,
                        "size": 1
                    },
                    {
                        "community_id": 12,
                        "size": 1
                    },
                    {
                        "community_id": 13,
                        "size": 1
                    },
                    {
                        "community_id": 14,
                        "size": 1
                    },
                    {
                        "community_id": 15,
                        "size": 1
                    },
                    {
                        "community_id": 16,
                        "size": 1
                    }
                ]
            }
        },
        "nodes": [
            {
                "name": "Eduardo Fausto Kuster Cid",
                "node_type": "person",
                "classification": "researcher",
                "classification_confidence": "high",
                "was_student": false,
                "was_staff": true,
                "campus_id": 2,
                "campus_name": "Vitória",
                "degree": 0,
                "weighted_degree": 0,
                "degree_centrality": 0.0,
                "betweenness_centrality": 0.0,
                "clustering_coefficient": 0,
                "community_id": 0,
                "is_articulation_point": false,
                "is_hub": false,
                "id": 18
            },
            {
                "name": "Sabrine Lino Pinto",
                "node_type": "person",
                "classification": "researcher",
                "classification_confidence": "high",
                "was_student": true,
                "was_staff": true,
                "campus_id": 1,
                "campus_name": "Vila Velha",
                "degree": 0,
                "weighted_degree": 0,
                "degree_centrality": 0.0,
                "betweenness_centrality": 0.0,
                "clustering_coefficient": 0,
                "community_id": 1,
                "is_articulation_point": false,
                "is_hub": false,
                "id": 19
            },
            {
                "name": "Aramis Cortes De Araujo Junior",
                "node_type": "person",
                "classification": "researcher",
                "classification_confidence": "high",
                "was_student": false,
                "was_staff": true,
                "campus_id": 5,
                "campus_name": "Alegre",
                "degree": 0,
                "weighted_degree": 0,
                "degree_centrality": 0.0,
                "betweenness_centrality": 0.0,
                "clustering_coefficient": 0,
                "community_id": 2,
                "is_articulation_point": false,
                "is_hub": false,
                "id": 152
            },
            {
                "name": "Levanildo Silva de Oliveira",
                "node_type": "person",
                "classification": "student",
                "classification_confidence": "medium",
                "was_student": true,
                "was_staff": false,
                "campus_id": 16,
                "campus_name": "Cefor",
                "degree": 0,
                "weighted_degree": 0,
                "degree_centrality": 0.0,
                "betweenness_centrality": 0.0,
                "clustering_coefficient": 0,
                "community_id": 3,
                "is_articulation_point": false,
                "is_hub": false,
                "id": 1689
            },
            {
                "name": "Adriana Luisa Lourenço Falcão",
                "node_type": "person",
                "classification": "researcher",
                "classification_confidence": "high",
                "was_student": false,
                "was_staff": true,
                "campus_id": 2,
                "campus_name": "Vitória",
                "degree": 0,
                "weighted_degree": 0,
                "degree_centrality": 0.0,
                "betweenness_centrality": 0.0,
                "clustering_coefficient": 0,
                "community_id": 4,
                "is_articulation_point": false,
                "is_hub": false,
                "id": 1909
            },
            {
                "name": "Camille Altoé Calatrone",
                "node_type": "person",
                "classification": "researcher",
                "classification_confidence": "high",
                "was_student": false,
                "was_staff": true,
                "campus_id": 1,
                "campus_name": "Vila Velha",
                "degree": 0,
                "weighted_degree": 0,
                "degree_centrality": 0.0,
                "betweenness_centrality": 0.0,
                "clustering_coefficient": 0,
                "community_id": 5,
                "is_articulation_point": false,
                "is_hub": false,
                "id": 1910
            },
            {
                "name": "Izabella Capucho Céllia Guimarães",
                "node_type": "person",
                "classification": "student",
                "classification_confidence": "medium",
                "was_student": true,
                "was_staff": false,
                "campus_id": 2,
                "campus_name": "Vitória",
                "degree": 0,
                "weighted_degree": 0,
                "degree_centrality": 0.0,
                "betweenness_centrality": 0.0,
                "clustering_coefficient": 0,
                "community_id": 6,
                "is_articulation_point": false,
                "is_hub": false,
                "id": 1911
            },
            {
                "name": "Lucas Rodrigues Barreto",
                "node_type": "person",
                "classification": "researcher",
                "classification_confidence": "high",
                "was_student": true,
                "was_staff": true,
                "campus_id": 2,
                "campus_name": "Vitória",
                "degree": 0,
                "weighted_degree": 0,
                "degree_centrality": 0.0,
                "betweenness_centrality": 0.0,
                "clustering_coefficient": 0,
                "community_id": 7,
                "is_articulation_point": false,
                "is_hub": false,
                "id": 1912
            },
            {
                "name": "Andressa Lemos Fernandes",
                "node_type": "person",
                "classification": "researcher",
                "classification_confidence": "high",
                "was_student": false,
                "was_staff": true,
                "campus_id": 2,
                "campus_name": "Vitória",
                "degree": 0,
                "weighted_degree": 0,
                "degree_centrality": 0.0,
                "betweenness_centrality": 0.0,
                "clustering_coefficient": 0,
                "community_id": 8,
                "is_articulation_point": false,
                "is_hub": false,
                "id": 1913
            },
            {
                "name": "Geisa Correa Louback",
                "node_type": "person",
                "classification": "researcher",
                "classification_confidence": "high",
                "was_student": true,
                "was_staff": true,
                "campus_id": 5,
                "campus_name": "Alegre",
                "degree": 0,
                "weighted_degree": 0,
                "degree_centrality": 0.0,
                "betweenness_centrality": 0.0,
                "clustering_coefficient": 0,
                "community_id": 9,
                "is_articulation_point": false,
                "is_hub": false,
                "id": 1914
            },
            {
                "name": "Roberto Márcio da Silveira",
                "node_type": "person",
                "classification": "researcher",
                "classification_confidence": "high",
                "was_student": false,
                "was_staff": true,
                "campus_id": 2,
                "campus_name": "Vitória",
                "degree": 0,
                "weighted_degree": 0,
                "degree_centrality": 0.0,
                "betweenness_centrality": 0.0,
                "clustering_coefficient": 0,
                "community_id": 10,
                "is_articulation_point": false,
                "is_hub": false,
                "id": 1915
            },
            {
                "name": "Ana Carolina dos Reis Santos",
                "node_type": "person",
                "classification": "student",
                "classification_confidence": "medium",
                "was_student": true,
                "was_staff": false,
                "campus_id": 2,
                "campus_name": "Vitória",
                "degree": 0,
                "weighted_degree": 0,
                "degree_centrality": 0.0,
                "betweenness_centrality": 0.0,
                "clustering_coefficient": 0,
                "community_id": 11,
                "is_articulation_point": false,
                "is_hub": false,
                "id": 1916
            },
            {
                "name": "Jéssica Benedita Entrin Câmara",
                "node_type": "person",
                "classification": "student",
                "classification_confidence": "medium",
                "was_student": true,
                "was_staff": false,
                "campus_id": 2,
                "campus_name": "Vitória",
                "degree": 0,
                "weighted_degree": 0,
                "degree_centrality": 0.0,
                "betweenness_centrality": 0.0,
                "clustering_coefficient": 0,
                "community_id": 12,
                "is_articulation_point": false,
                "is_hub": false,
                "id": 1917
            },
            {
                "name": "Layane de Oliveira Ferreira",
                "node_type": "person",
                "classification": "student",
                "classification_confidence": "medium",
                "was_student": true,
                "was_staff": false,
                "campus_id": 2,
                "campus_name": "Vitória",
                "degree": 0,
                "weighted_degree": 0,
                "degree_centrality": 0.0,
                "betweenness_centrality": 0.0,
                "clustering_coefficient": 0,
                "community_id": 13,
                "is_articulation_point": false,
                "is_hub": false,
                "id": 1918
            },
            {
                "name": "Letícia Ferreira Dias",
                "node_type": "person",
                "classification": "student",
                "classification_confidence": "medium",
                "was_student": true,
                "was_staff": false,
                "campus_id": 2,
                "campus_name": "Vitória",
                "degree": 0,
                "weighted_degree": 0,
                "degree_centrality": 0.0,
                "betweenness_centrality": 0.0,
                "clustering_coefficient": 0,
                "community_id": 14,
                "is_articulation_point": false,
                "is_hub": false,
                "id": 1919
            },
            {
                "name": "Maria Aparecida Beltrame Milanesi",
                "node_type": "person",
                "classification": "student",
                "classification_confidence": "medium",
                "was_student": true,
                "was_staff": false,
                "campus_id": 2,
                "campus_name": "Vitória",
                "degree": 0,
                "weighted_degree": 0,
                "degree_centrality": 0.0,
                "betweenness_centrality": 0.0,
                "clustering_coefficient": 0,
                "community_id": 15,
                "is_articulation_point": false,
                "is_hub": false,
                "id": 1920
            },
            {
                "name": "Yasmin dos Santos Dias",
                "node_type": "person",
                "classification": "student",
                "classification_confidence": "medium",
                "was_student": true,
                "was_staff": false,
                "campus_id": 2,
                "campus_name": "Vitória",
                "degree": 0,
                "weighted_degree": 0,
                "degree_centrality": 0.0,
                "betweenness_centrality": 0.0,
                "clustering_coefficient": 0,
                "community_id": 16,
                "is_articulation_point": false,
                "is_hub": false,
                "id": 1921
            }
        ],
        "edges": []
    }
}